mysqlsheet/__init__.py
mysqlsheet/mysqlsheet.py
mysqlsheet-1.1.0.dist-info/LICENSE
mysqlsheet-1.1.0.dist-info/METADATA
mysqlsheet-1.1.0.dist-info/WHEEL
mysqlsheet-1.1.0.dist-info/entry_points.txt
mysqlsheet-1.1.0.dist-info/top_level.txt
mysqlsheet-1.1.0.dist-info/RECORD
